{"re_stat": 90, "gender": "Male", "race": "Half-elf", "199": ["Tumbling Attack", "AG/ST", "NULL", "5", "arms", 0, 0, 0, 0, 0, 0, 11, 0, 0, 11], "198": ["Tumbling", "AG/SD", "NULL", "3", "athletic", 0, 0, 0, 0, 0, 0, 5, 0, 0, 5], "195": ["Transcend Armor", "NA", "NULL", "6", "magical", 0, 0, 0, 0, 0, 0, 0, 0, 27, 27], "194": ["Trading Lore", "ME/RE", "NULL", "2/5", "academic", 0, 0, 0, 0, 0, 0, 21, 0, 18, 39], "197": ["Trickery", "PR/QU", "NULL", "3", "subterfuge", 0, 0, 0, 0, 0, 0, 25, 0, 0, 25], "196": ["Trap-Building", "RE/EM", "NULL", "3/6", "subterfuge", 0, 0, 0, 0, 0, 0, 13, 0, 0, 13], "191": ["Time Sense", "IN/ME", "NULL", "1/4", "perception", 0, 0, 0, 2, 0, 10, 21, 0, 0, 31], "190": ["Tightrope Walking", "AG/SD", "NULL", "3", "athletic", 0, 0, 0, 0, 0, 0, 5, 0, 0, 5], "193": ["Trading", "RE/EM", "NULL", "3/5", "linguistic", 0, 0, 0, 0, 0, 0, 13, 0, 0, 13], "192": ["Tracking", "IN/RE", "NULL", "3", "perception", 0, 0, 0, 0, 0, 0, 9, 0, 0, 9], "270": ["Unhorsing", "ST/ST/AG", "NULL", "18", "arms", 0, 0, 0, 0, 0, 0, 11, 0, 0, 11], "271": ["Weapon/Armor Maintenance", "AG/SD", "NULL", "3", "general", 0, 0, 0, 0, 0, 0, 5, 0, 0, 5], "272": ["Weapon Snare", "QU/AG", "NULL", "6", "arms", 0, 0, 0, 0, 0, 0, 16, 0, 0, 16], "273": ["Weapon Trickery", "AG/QU", "NULL", "9", "arms", 0, 0, 0, 0, 0, 0, 16, 0, 0, 16], "274": ["Whip Grapple : 1", "AG/ST", "NULL", "9", "arms", 0, 0, 0, 0, 0, 0, 11, 0, 0, 11], "275": ["Whip Grapple : 2", "AG/ST", "NULL", "9", "arms", 0, 0, 0, 0, 0, 0, 11, 0, 0, 11], "276": ["Whip Grapple : 3", "AG/ST", "NULL", "9", "arms", 0, 0, 0, 0, 0, 0, 11, 0, 0, 11], "277": ["Whip Grapple : 4", "AG/ST", "NULL", "9", "arms", 0, 0, 0, 0, 0, 0, 11, 0, 0, 11], "278": ["TWC - Scimitar: RH", "ST/ST/AG", "1-HS", "20", "arms", 0, 0, 0, 0, 0, 0, 11, 0, 0, 11], "279": ["TWC - Scimitar: LH", "ST/ST/AG", "1-HS", "20", "arms", 0, 0, 0, 0, 0, 0, 11, 0, 0, 11], "lang3": ["Grey Elf", 4, 4], "lang2": ["Wood Elf", 6, 6], "at_min_mod": "0", "at_qu_pen": "0", "108": ["M.A. Sweeps Rank4", "AG/AG/ST", "NULL", "9", "arms", 0, 0, 0, 0, 0, 0, 12, 0, 0, 12], "109": ["Mapping", "RE/ME", "NULL", "3", "academic", 0, 0, 0, 1, 0, 5, 21, 0, 18, 44], "102": ["M.A. Strikes Rank2", "ST/ST/AG", "NULL", "9", "arms", 0, 0, 0, 0, 0, 0, 11, 0, 0, 11], "103": ["M.A. Strikes Rank3", "ST/ST/AG", "NULL", "9", "arms", 0, 0, 0, 0, 0, 0, 11, 0, 0, 11], "100": ["Maneuvering in Plate", "AG", "NULL", "11", "arms", 0, 0, 0, 0, 0, 0, 13, 0, 0, 13], "101": ["M.A. Strikes Rank1", "ST/ST/AG", "NULL", "9", "arms", 0, 0, 0, 0, 0, 0, 11, 0, 0, 11], "106": ["M.A. Sweeps Rank2", "AG/AG/ST", "NULL", "9", "arms", 0, 0, 0, 0, 0, 0, 12, 0, 0, 12], "107": ["M.A. Sweeps Rank3", "AG/AG/ST", "NULL", "9", "arms", 0, 0, 0, 0, 0, 0, 12, 0, 0, 12], "104": ["M.A. Strikes Rank4", "ST/ST/AG", "NULL", "9", "arms", 0, 0, 0, 0, 0, 0, 11, 0, 0, 11], "105": ["M.A. Sweeps Rank1", "AG/AG/ST", "NULL", "9", "arms", 0, 0, 0, 0, 0, 0, 12, 0, 0, 12], "39": ["Control Lycanthropy", "SD", "NULL", "1/4", "concentration", 0, 0, 0, 0, 0, 0, -2, 0, 9, 7], "38": ["Contortions", "AG/SD", "NULL", "5", "athletic", 0, 0, 0, 0, 0, 0, 5, 0, 0, 5], "33": ["Camouflage", "RE/IN", "NULL", "5", "subterfuge", 0, 0, 0, 0, 0, 0, 9, 0, 0, 9], "32": ["Bribery", "PR/RE", "NULL", "2/6", "subterfuge", 0, 0, 0, 0, 0, 0, 20, 0, 0, 20], "31": ["Brawling", "RE/IN", "NULL", "18", "arms", 0, 0, 0, 0, 0, 0, 9, 0, 0, 9], "30": ["Body Development", "CO", "NULL", "8", "body development", 0, 1, 1, 7, 0, 45, 12, 0, 0, 57], "37": ["Climbing", "AG", "NULL", "6", "athletic", 0, 1, 0, 1, 0, 10, 13, 0, 0, 23], "36": ["Circle Lore", "ME/RE", "NULL", "1/4", "magical", 0, 0, 0, 0, 0, 0, 21, 0, 27, 48], "35": ["Channeling", "IN", "NULL", "7", "magical", 0, 0, 0, 0, 0, 0, 9, 0, 27, 36], "34": ["Caving", "SD/RE", "NULL", "3", "outdoor", 0, 0, 0, 0, 0, 0, 4, 0, 0, 4], "eye": "Hazel", "6": ["Adrenal Move: Leaping", "PR/SD", "NULL", "6", "concentration", 0, 0, 0, 0, 0, 0, 14, 0, 9, 23], "99": ["Maneuvering in Chain", "AG", "NULL", "10", "arms", 0, 0, 0, 0, 0, 0, 13, 0, 0, 13], "98": ["Maneuvering in Rigid Leather", "AG", "NULL", "9", "arms", 0, 0, 0, 0, 0, 0, 13, 0, 0, 13], "91": ["Lip Reading", "IN/RE", "NULL", "2/4", "linguistic", 0, 0, 0, 0, 0, 0, 9, 0, 0, 9], "90": ["Linguistics", "NA", "NULL", "2/*", "linguistic", 0, 0, 0, 0, 0, 0, 0, 0, 0, 0], "93": ["Locate Secret Opening", "IN/RE", "NULL", "3/6", "perception", 0, 0, 0, 1, 0, 5, 9, 0, 0, 14], "92": ["Loading", "EM/RE", "NULL", "3", "outdoor", 0, 0, 0, 0, 0, 0, 13, 0, 0, 13], "95": ["Magical Language", "NA", "NULL", "1/*", "magical", 0, 0, 0, 0, 0, 0, 0, 0, 27, 27], "94": ["Lock Lore", "ME/RE", "NULL", "2/4", "academic", 0, 0, 0, 0, 0, 0, 21, 0, 18, 39], "97": ["Maneuvering in Soft Leather", "AG", "NULL", "9", "arms", 0, 0, 0, 0, 0, 0, 13, 0, 0, 13], "96": ["Magical Ritual", "RE/ME", "NULL", "1/4", "magical", 0, 0, 0, 0, 0, 0, 21, 0, 27, 48], "at_max_mod": "0", "poimod": 12, "agmb": 0, "238": ["Play Instruments: Category 2", "AG/ME", "NULL", "3/7", "general", 0, 0, 0, 0, 0, 0, 23, 0, 0, 23], "239": ["Play Instruments: Category 3", "AG/ME", "NULL", "3", "general", 0, 0, 0, 0, 0, 0, 23, 0, 0, 23], "234": ["War Hammer", "ST/ST/AG", "1-HC", "20", "arms", 0, 0, 0, 0, 0, 0, 11, 0, 0, 11], "235": ["War Mattock", "ST/ST/AG", "2-H", "9", "arms", 0, 0, 0, 0, 0, 0, 11, 0, 0, 11], "236": ["Whip", "ST/ST/AG", "1-HC", "20", "arms", 0, 0, 0, 0, 0, 0, 11, 0, 0, 11], "237": ["Riding - Horse", "EM/AG", "NULL", "3", "outdoor", 0, 1, 0, 2, 0, 15, 15, 0, 0, 30], "230": ["Short Sword", "ST/ST/AG", "1-HS", "20", "arms", 0, 0, 0, 0, 0, 0, 11, 0, 0, 11], "231": ["Sling", "AG/AG/ST", "Missile", "20", "arms", 0, 0, 0, 0, 0, 0, 12, 0, 0, 12], "232": ["Spear", "ST/ST/AG", "Polearm", "20", "arms", 0, 0, 0, 0, 0, 0, 11, 0, 0, 11], "233": ["Two-Handed Sword", "ST/ST/AG", "2-H", "9", "arms", 0, 0, 0, 0, 0, 0, 11, 0, 0, 11], "1": ["Acrobatics", "AG/QU", "NULL", "3", "athletic", 0, 0, 0, 0, 0, 0, 16, 0, 0, 16], "146": ["Region Lore", "RE/ME", "NULL", "2/6", "outdoor", 0, 1, 1, 4, 0, 30, 21, 0, 0, 51], "147": ["Reverse Stroke", "AG/RE", "NULL", "20", "arms", 0, 0, 0, 0, 0, 0, 11, 0, 0, 11], "144": ["Rappling", "AG", "NULL", "6", "athletic", 0, 0, 0, 0, 0, 0, 13, 0, 0, 13], "145": ["Read Tracks", "IN/RE", "NULL", "3/6", "perception", 0, 0, 0, 0, 0, 0, 9, 0, 0, 9], "142": ["Public Speaking", "EM/PR", "NULL", "2/6", "linguistic", 0, 0, 0, 0, 0, 0, 23, 0, 0, 23], "143": ["Racial History", "ME/RE", "NULL", "1/4", "academic", 0, 1, 1, 2, 0, 20, 21, 0, 18, 59], "140": ["Power Projection", "NA", "NULL", "2/4", "magical", 0, 0, 0, 0, 0, 0, 0, 0, 27, 27], "141": ["Propaganda", "IN/EM", "NULL", "3/5", "linguistic", 0, 0, 0, 0, 0, 0, 13, 0, 0, 13], "148": ["Rope Mastery", "ME/AG", "NULL", "3", "general", 0, 1, 0, 2, 0, 15, 23, 0, 0, 38], "149": ["Rowing", "ST/SD", "NULL", "3", "athletic", 0, 0, 0, 0, 0, 0, 4, 0, 0, 4], "cotb": 12, "133": ["Planetology", "RE/EM", "NULL", "4", "academic", 0, 0, 0, 0, 0, 0, 13, 0, 18, 31], "132": ["Pick Pockets", "AG/IN", "NULL", "3", "subterfuge", 0, 0, 0, 0, 0, 0, 11, 0, 0, 11], "131": ["Picking Locks", "IN/RE/AG", "NULL", "8", "subterfuge", 0, 0, 0, 0, 0, 0, 10, 0, 0, 10], "130": ["Physics", "RE/ME", "NULL", "3/7", "academic", 0, 0, 0, 0, 0, 0, 21, 0, 18, 39], "137": ["Poison Perception", "IN/RE", "NULL", "3", "perception", 0, 0, 0, 0, 0, 0, 9, 0, 0, 9], "136": ["Poison Lore", "ME/RE", "NULL", "2/6", "academic", 0, 0, 0, 0, 0, 0, 21, 0, 18, 39], "135": ["Poetic Improvisation", "IN/RE", "NULL", "2/6", "linguistic", 0, 0, 0, 0, 0, 0, 9, 0, 0, 9], "134": ["Play Instruments: Category 1", "AG/ME", "NULL", "2/6", "general", 0, 0, 0, 0, 0, 0, 23, 0, 0, 23], "helm": "Visored Helm", "139": ["Power Perception", "IN/RE", "NULL", "1/3", "magical", 0, 0, 0, 0, 0, 0, 9, 0, 27, 36], "138": ["Pole Vaulting", "ST/AG", "NULL", "5", "athletic", 0, 0, 0, 0, 0, 0, 11, 0, 0, 11], "24": ["Basic Math", "RE/ME", "NULL", "2/6", "academic", 0, 1, 0, 2, 0, 15, 21, 0, 18, 54], "25": ["Beast Mastery", "EM/PR", "NULL", "4", "outdoor", 0, 0, 0, 0, 0, 0, 23, 0, 0, 23], "26": ["Begging", "PR/EM", "NULL", "2/6", "subterfuge", 0, 0, 0, 0, 0, 0, 23, 0, 0, 23], "27": ["Biochemistry", "IN/RE", "NULL", "5", "academic", 0, 0, 0, 0, 0, 0, 9, 0, 18, 27], "20": ["Armor Evaluation", "IN/RE", "NULL", "4", "general", 0, 0, 0, 0, 0, 0, 9, 0, 0, 9], "21": ["Astronomy", "ME/RE", "NULL", "3/7", "academic", 0, 0, 0, 0, 0, 0, 21, 0, 18, 39], "22": ["Athletic Games", "ST/AG/QU", "NULL", "6", "athletic", 0, 0, 0, 0, 0, 0, 14, 0, 0, 14], "23": ["Attunement", "EM/IN", "NULL", "1/4", "magical", 0, 0, 2, 10, 0, 54, 13, 0, 27, 94], "28": ["Boat Pilot", "ME/AG", "NULL", "2/6", "academic", 0, 0, 0, 0, 0, 0, 23, 0, 18, 41], "29": ["Body Damage Stablize", "SD/EM", "NULL", "3/5", "concentration", 0, 0, 0, 0, 0, 0, 7, 0, 9, 16], "hp_base": 8, "name": "Uldar", "sd_stat": 84, "em_stat": 96, "weight": "160", "hitdie": "D10", "metb": 8, "88": ["Leather Working", "AG/RE", "NULL", "3", "general", 0, 0, 0, 0, 0, 0, 11, 0, 0, 11], "89": ["Lie Perception", "IN/RE", "NULL", "2/5", "perception", 0, 0, 0, 3, 0, 15, 9, 0, 0, 24], "82": ["Iai", "QU/AG", "NULL", "15", "arms", 0, 0, 0, 0, 0, 0, 16, 0, 0, 16], "83": ["Interrogation", "RE/AG", "NULL", "3", "social", 0, 0, 0, 0, 0, 0, 11, 0, 0, 11], "80": ["Hostile Environments", "AG/SD", "NULL", "3", "outdoor", 0, 0, 0, 0, 0, 0, 5, 0, 0, 5], "81": ["Hypnosis", "PR/SD", "NULL", "2/4", "medical", 0, 0, 0, 0, 0, 0, 14, 0, 0, 14], "86": ["Lancing", "ST/AG", "NULL", "18", "arms", 0, 0, 0, 0, 0, 0, 11, 0, 0, 11], "87": ["Leadership", "PR/RE", "NULL", "2/4", "social", 0, 0, 0, 0, 0, 0, 20, 0, 0, 20], "84": ["Juggling", "AG/IN", "NULL", "3", "athletic", 0, 0, 0, 0, 0, 0, 11, 0, 0, 11], "85": ["Jumping", "ST/AG", "NULL", "4", "athletic", 0, 0, 0, 0, 0, 0, 11, 0, 0, 11], "7": ["Adrenal Move: Quick Draw", "PR/SD", "NULL", "4", "concentration", 0, 0, 0, 0, 0, 0, 14, 0, 9, 23], "st_stat": 77, "armorType": 1, "sheildType": "Wall Shield", "245": ["Awakening", "IN", "NULL", "18", "arms", 0, 0, 0, 0, 0, 0, 9, 0, 0, 9], "244": ["Airborne Combat", "AG/QU", "NULL", "18", "arms", 0, 0, 0, 0, 0, 0, 16, 0, 0, 16], "247": ["Blind Fighting:Hearing", "RE/EM", "NULL", "10", "arms", 0, 0, 0, 0, 0, 0, 13, 0, 0, 13], "246": ["Battle Perception", "IN/ME", "NULL", "2/4", "academic", 0, 0, 0, 0, 0, 0, 21, 0, 18, 39], "241": ["Shield Bash", "ST/ST/AG", "1-HC", "20", "arms", 0, 0, 0, 0, 0, 0, 11, 0, 0, 11], "240": ["Adrenal Defense", "NA", "NULL", "20", "concentration", 0, 0, 0, 0, 0, 0, 0, 0, 9, 9], "243": ["Adrenal Spell Avoidance", "PR", "NULL", "6", "concentration", 0, 0, 0, 0, 0, 0, 30, 0, 9, 39], "242": ["Directed Spells - Adrenal Focus", "AG", "NULL", "1/4", "directed spells", 0, 0, 0, 0, 0, 0, 13, 0, 27, 40], "249": ["Blind Fighting:Touch", "RE/EM", "NULL", "25", "arms", 0, 0, 0, 0, 0, 0, 13, 0, 0, 13], "248": ["Blind Fighting:Smell", "RE/ME", "NULL", "20", "arms", 0, 0, 0, 0, 0, 0, 21, 0, 0, 21], "in_stat": 88, "re_pot": 90, "prmb": 15, "179": ["Stunned Maneuvering", "SD", "NULL", "5", "arms", 0, 0, 0, 0, 0, 0, -2, 0, 0, -2], "178": ["Streetwise", "PR/IN", "NULL", "3", "outdoor", 0, 0, 0, 0, 0, 0, 19, 0, 0, 19], "177": ["Stone Lore", "ME/RE", "NULL", "1/4", "academic", 0, 0, 0, 0, 0, 0, 21, 0, 18, 39], "176": ["Stone Evaluation", "IN/RE", "NULL", "2/4", "general", 0, 0, 0, 0, 0, 0, 9, 0, 0, 9], "175": ["Stone Crafts", "SD/AG", "NULL", "3", "general", 0, 0, 0, 0, 0, 0, 5, 0, 0, 5], "174": ["Stilt Walking", "ST/AG", "NULL", "4", "athletic", 0, 0, 0, 0, 0, 0, 11, 0, 0, 11], "173": ["Star-Gazing", "ME/IN", "NULL", "2/6", "academic", 0, 0, 0, 0, 0, 0, 21, 0, 18, 39], "172": ["Stalk & Hide", "AG/SD", "NULL", "5", "subterfuge", 0, 1, 0, 3, 0, 20, 5, 11, 0, 36], "171": ["Sprinting", "QU", "NULL", "3", "athletic", 0, 0, 0, 0, 0, 0, 20, 0, 0, 20], "170": ["Spell Mastery", "EM", "NULL", "2/5", "magical", 0, 0, 0, 3, 0, 15, 17, 0, 27, 59], "182": ["Surgery", "SD/EM/IN", "NULL", "6", "medical", 0, 0, 0, 0, 0, 0, 8, 0, 0, 8], "183": ["Surveillance", "IN/SD", "NULL", "2/6", "perception", 0, 0, 0, 0, 0, 0, 3, 0, 0, 3], "180": ["Subduing", "AG/QU", "NULL", "6", "arms", 0, 0, 0, 0, 0, 0, 16, 0, 0, 16], "181": ["Surfing", "AG/SD", "NULL", "3", "athletic", 0, 0, 0, 0, 0, 0, 5, 0, 0, 5], "186": ["Tactical Games", "RE/ME", "NULL", "1/4", "general", 0, 0, 0, 1, 0, 5, 21, 0, 0, 26], "187": ["Tactics", "IN/RE", "NULL", "2/4", "academic", 0, 0, 0, 0, 0, 0, 9, 0, 18, 27], "184": ["Swimming", "AG", "NULL", "3", "athletic", 0, 1, 1, 3, 0, 25, 13, 0, 0, 38], "185": ["Symbol Lore", "ME/RE", "NULL", "1/4", "magical", 0, 0, 0, 0, 0, 0, 21, 0, 27, 48], "188": ["Tale Telling", "PR/ME", "NULL", "2/6", "linguistic", 0, 0, 0, 0, 0, 0, 31, 0, 0, 31], "189": ["Targeting Skill", "IN/AG", "NULL", "2/5", "magical", 0, 0, 0, 1, 0, 5, 11, 0, 27, 43], "memb": 25, "prtb": 15, "11": ["Advertising", "IN/RE", "NULL", "3/5", "general", 0, 0, 0, 0, 0, 0, 9, 0, 0, 9], "10": ["Advanced Math", "RE/ME", "NULL", "3/7", "academic", 0, 0, 0, 0, 0, 0, 21, 0, 18, 39], "13": ["Ambush", "NA", "NULL", "9", "deadly", 0, 0, 0, 0, 0, 0, 0, 0, 0, 0], "12": ["Alchemy", "RE/ME", "NULL", "2/4", "academic", 0, 0, 0, 0, 0, 0, 21, 0, 18, 39], "15": ["Animal Healing", "EM/RE", "NULL", "2/6", "medical", 0, 0, 0, 0, 0, 0, 13, 0, 0, 13], "14": ["Animal Handling", "EM/PR", "NULL", "2/5", "outdoor", 0, 0, 0, 0, 0, 0, 23, 0, 0, 23], "17": ["Anthropology", "IN/EM", "NULL", "2/5", "academic", 0, 0, 0, 0, 0, 0, 13, 0, 18, 31], "16": ["Animal Training", "EM/PR", "NULL", "4", "outdoor", 0, 0, 0, 0, 0, 0, 23, 0, 0, 23], "19": ["Architecture", "RE/ME", "NULL", "2/5", "academic", 0, 0, 0, 1, 0, 5, 21, 0, 18, 44], "18": ["Appraisal", "RE/ME", "NULL", "3/7", "general", 0, 0, 0, 1, 0, 5, 21, 0, 0, 26], "armGrea": "", "pro_name": "Magician", "62": ["Faerie Lore", "ME/RE", "NULL", "1/2", "academic", 0, 0, 0, 5, 0, 25, 21, 0, 18, 64], "co_pot": 82, "lang1": ["Common", 6, 4], "sd_pot": 85, "stmb": 0, "realm": "EM", "201": ["Use/Remove Poison", "AG/IN", "NULL", "2/6", "deadly", 0, 0, 0, 0, 0, 0, 11, 0, 0, 11], "200": ["Tumbling Evasion", "AG/QU", "NULL", "3", "arms", 0, 0, 0, 0, 0, 0, 16, 0, 0, 16], "203": ["Warding Lore", "ME/RE", "NULL", "2/4", "magical", 0, 0, 0, 0, 0, 0, 21, 0, 27, 48], "202": ["Ventriloquism", "SD/IN", "NULL", "3/6", "linguistic", 0, 0, 0, 0, 0, 0, 3, 0, 0, 3], "205": ["Weapon Evaluation", "IN/RE", "NULL", "4", "general", 0, 0, 0, 0, 0, 0, 9, 0, 0, 9], "204": ["Weather-Watching", "IN/EM", "NULL", "1/4", "academic", 0, 0, 0, 0, 0, 0, 13, 0, 18, 31], "207": ["Yado", "QU/AG", "NULL", "6", "arms", 0, 0, 0, 0, 0, 0, 16, 0, 0, 16], "206": ["Wood Crafts", "AG/EM", "NULL", "3", "general", 0, 0, 0, 0, 0, 0, 15, 0, 0, 15], "209": ["Bola", "AG/AG/ST", "Thrown", "20", "arms", 0, 0, 0, 0, 0, 0, 12, 0, 0, 12], "208": ["Battle Axe", "ST/ST/AG", "2-H", "9", "arms", 0, 0, 0, 0, 0, 0, 11, 0, 0, 11], "dismod": 62, "77": ["Herding", "EM/PR", "NULL", "2/6", "outdoor", 0, 0, 0, 0, 0, 0, 23, 0, 0, 23], "76": ["Herb Lore", "ME/RE", "NULL", "2/6", "academic", 0, 0, 0, 0, 0, 0, 21, 0, 18, 39], "75": ["Heraldry", "ME/RE", "NULL", "3/5", "academic", 0, 0, 0, 0, 0, 0, 21, 0, 18, 39], "74": ["Grappling Hook", "AG", "NULL", "3", "arms", 0, 0, 0, 0, 0, 0, 13, 0, 0, 13], "73": ["Gimmickry", "IN/RE", "NULL", "3", "general", 0, 0, 0, 0, 0, 0, 9, 0, 0, 9], "72": ["General Perception", "IN/IN/RE", "NULL", "3", "perception", 0, 0, 1, 8, 0, 45, 9, 0, 0, 54], "71": ["Gambling", "ME/PR", "NULL", "2/4", "social", 0, 0, 0, 0, 0, 0, 31, 0, 0, 31], "70": ["Frenzy", "EM/SD", "NULL", "5", "concentration", 0, 0, 0, 0, 0, 0, 7, 0, 9, 16], "79": ["Horticulture", "RE/EM", "NULL", "2/6", "general", 0, 0, 0, 0, 0, 0, 13, 0, 0, 13], "78": ["Hide Item", "RE/IN", "NULL", "5", "subterfuge", 0, 0, 0, 0, 0, 0, 9, 0, 0, 9], "2": ["Acting", "PR/EM", "NULL", "3/6", "subterfuge", 0, 0, 0, 0, 0, 0, 23, 0, 0, 23], "exp": 134011, "qu_pot": 96, "legGrea": "", "8": ["Adrenal Move: Speed", "PR/SD", "NULL", "6", "concentration", 0, 0, 0, 0, 0, 0, 14, 0, 9, 23], "120": ["Military Organization", "PR/RE", "NULL", "3/6", "academic", 0, 0, 0, 0, 0, 0, 20, 0, 18, 38], "121": ["Mimicry", "IN/SD", "NULL", "2/6", "linguistic", 0, 0, 0, 0, 0, 0, 3, 0, 0, 3], "122": ["Mimery", "AG/SD", "NULL", "3/6", "subterfuge", 0, 0, 0, 0, 0, 0, 5, 0, 0, 5], "123": ["Mining", "RE/IN", "NULL", "3", "academic", 0, 0, 0, 0, 0, 0, 9, 0, 18, 27], "124": ["Missile Artillery", "IN/AG", "NULL", "3/6", "arms", 0, 0, 0, 0, 0, 0, 11, 0, 0, 11], "125": ["Mnemonics", "ME/SD", "NULL", "1/4", "concentration", 0, 0, 0, 3, 0, 15, 15, 0, 9, 39], "126": ["Music", "AG/EM", "NULL", "2/6", "linguistic", 0, 0, 0, 0, 0, 0, 15, 0, 0, 15], "127": ["Navigation", "RE/IN", "NULL", "2/6", "academic", 0, 0, 0, 0, 0, 0, 9, 0, 18, 27], "128": ["Painting", "IN/AG", "NULL", "2/4", "general", 0, 0, 0, 0, 0, 0, 11, 0, 0, 11], "129": ["Phil./Relig. Doctrine", "ME/RE", "NULL", "1/2", "academic", 1, 0, 2, 4, 0, 35, 21, 0, 18, 74], "dp": 50.1, "st_pot": 77, "tempdp": 50, "at_miss_pen": "0", "3": ["Administration", "RE/PR", "NULL", "2/5", "academic", 0, 0, 0, 0, 0, 0, 20, 0, 18, 38], "comb": 0, "sdtb": -2, "252": ["Defensive Weaving", "NA", "NULL", "20", "concentration", 0, 0, 0, 0, 0, 0, 0, 0, 9, 9], "height": "6'3\"", "60": ["Duping", "PR", "NULL", "3/5", "social", 0, 0, 0, 0, 0, 0, 30, 0, 0, 30], "61": ["Engineering", "RE/ME", "NULL", "2/6", "academic", 0, 0, 0, 0, 0, 0, 21, 0, 18, 39], "258": ["Donning/Doffing Armor:Chain", "QU/AG", "NULL", "10", "arms", 0, 0, 0, 0, 0, 0, 16, 0, 0, 16], "63": ["Falsification", "SD/RE", "NULL", "3", "subterfuge", 0, 0, 0, 0, 0, 0, 4, 0, 0, 4], "64": ["Fauna Lore", "ME/RE", "NULL", "2/5", "academic", 0, 0, 0, 0, 0, 0, 21, 0, 18, 39], "65": ["First Aid", "SD/EM", "NULL", "2/6", "medical", 0, 1, 1, 5, 0, 35, 7, 0, 0, 42], "66": ["Fletching", "AG/SD", "NULL", "2/6", "general", 0, 0, 0, 0, 0, 0, 5, 0, 0, 5], "essmod": 12, "68": ["Fying/Gliding", "ME/RE", "NULL", "3", "athletic", 0, 0, 0, 0, 0, 0, 21, 0, 0, 21], "69": ["Foraging", "IN/ME", "NULL", "2/6", "outdoor", 0, 0, 0, 1, 0, 5, 21, 0, 0, 26], "250": ["Blind Fighting:Intuition", "IN", "NULL", "25", "arms", 0, 0, 0, 0, 0, 0, 9, 0, 0, 9], "251": ["Cryptography", "IN/RE", "NULL", "2/6", "linguistic", 0, 0, 0, 0, 0, 0, 9, 0, 0, 9], "256": ["Donning/Doffing Armor:SL", "QU/AG", "NULL", "9", "arms", 0, 0, 0, 0, 0, 0, 16, 0, 0, 16], "257": ["Donning/Doffing Armor:RL", "QU/AG", "NULL", "9", "arms", 0, 0, 0, 0, 0, 0, 16, 0, 0, 16], "254": ["Directed Strength", "SD", "NULL", "6", "arms", 0, 0, 0, 0, 0, 0, -2, 0, 0, -2], "255": ["Distract Foe", "AG/QU", "NULL", "9", "arms", 0, 0, 0, 0, 0, 0, 16, 0, 0, 16], "retb": 10, "in_pot": 90, "shieldMiDB": "40", "168": ["Spacial Locate Awareness", "IN", "NULL", "2/5", "concentration", 0, 0, 0, 0, 0, 0, 9, 0, 9, 18], "169": ["Spell List", "EM", "NULL", "1/*", "magical", 0, 0, 4, 24, 0, 78, 17, 0, 27, 122], "164": ["Skating", "AG/SD", "NULL", "3", "athletic", 0, 0, 0, 0, 0, 0, 5, 0, 0, 5], "165": ["Skiing", "AG/SD", "NULL", "3", "athletic", 0, 0, 0, 0, 0, 0, 5, 0, 0, 5], "166": ["Skinning", "AG/IN", "NULL", "3", "general", 0, 0, 0, 0, 0, 0, 11, 0, 0, 11], "167": ["Smithing", "ST/AG", "NULL", "3", "general", 0, 0, 0, 0, 0, 0, 11, 0, 0, 11], "160": ["Set Traps", "RE/AG", "NULL", "7", "subterfuge", 0, 0, 0, 0, 0, 0, 11, 0, 0, 11], "161": ["Signaling", "ME/SD", "NULL", "1/5", "linguistic", 0, 0, 0, 0, 0, 0, 15, 0, 0, 15], "162": ["Singing", "PR/IN", "NULL", "2/6", "linguistic", 0, 0, 0, 0, 0, 0, 19, 0, 0, 19], "163": ["Silent Kill", "AG/IN", "NULL", "6", "deadly", 0, 0, 0, 0, 0, 0, 11, 0, 0, 11], "qumb": 0, "sdmb": 0, "remb": 0, "sttb": 10, "agtb": 13, "chanmod": 4, "helmMaDB": "5", "emtb": 17, "qutb": 20, "9": ["Adrenal Move: Strength", "PR/SD", "NULL", "6", "concentration", 0, 0, 0, 0, 0, 0, 14, 0, 9, 23], "shieldMaDB": "30", "pr_stat": 75, "em_pot": 96, "216": ["Hand Axe", "ST/ST/AG", "1-HS", "20", "arms", 0, 0, 0, 0, 0, 0, 11, 0, 0, 11], "217": ["Heavy Crossbow", "AG/AG/ST", "Missile", "20", "arms", 0, 0, 0, 0, 0, 0, 12, 0, 0, 12], "214": ["Falchion", "ST/ST/AG", "1-HS", "20", "arms", 0, 0, 0, 0, 0, 0, 11, 0, 0, 11], "215": ["Flail", "ST/ST/AG", "2-H", "9", "arms", 0, 0, 0, 0, 0, 0, 11, 0, 0, 11], "212": ["Composite Bow", "AG/AG/ST", "Missile", "20", "arms", 0, 0, 0, 0, 0, 0, 12, 0, 0, 12], "213": ["Dagger", "ST/ST/AG", "1-HS", "20", "arms", 0, 0, 0, 0, 0, 0, 11, 0, 0, 11], "210": ["Broadsword", "ST/ST/AG", "1-HS", "20", "arms", 0, 0, 0, 0, 0, 0, 11, 0, 0, 11], "211": ["Club", "ST/ST/AG", "1-HC", "20", "arms", 0, 0, 0, 0, 0, 0, 11, 0, 0, 11], "218": ["Javelin", "ST/ST/AG", "Polearm", "20", "arms", 0, 0, 0, 0, 0, 0, 11, 0, 0, 11], "219": ["Lance", "ST/ST/AG", "2-h", "NULL", "arms", 0, 0, 0, 0, 0, 0, 11, 0, 0, 11], "armorTypeDesc": "Skin", "4": ["Adrenal Move: Balance", "PR/SD", "NULL", "6", "concentration", 0, 0, 0, 0, 0, 0, 14, 0, 9, 23], "281": ["Directed Spells - Shock Bolt", "AG", "NULL", "1/4", "directed spells", 0, 0, 0, 4, 0, 20, 13, 0, 27, 60], "280": ["Dagger: Thrown", "AG/AG/ST", "Thrown", "20", "arms", 0, 0, 0, 0, 0, 0, 12, 0, 0, 12], "283": ["Directed Spells - Fire Bolt", "AG", "NULL", "1/4", "directed spells", 0, 0, 0, 8, 0, 40, 13, 0, 27, 80], "282": ["Directed Spells - Water Bolt", "AG", "NULL", "1/4", "directed spells", 0, 0, 0, 10, 0, 50, 13, 0, 27, 90], "285": ["Directed Spells - Plasma Bolt", "AG", "NULL", "1/4", "directed spells", 0, 0, 0, 0, 0, 0, 13, 0, 27, 40], "284": ["Directed Spells - Lightning Bolt", "AG", "NULL", "1/4", "directed spells", 0, 0, 0, 0, 0, 0, 13, 0, 27, 40], "287": ["Directed Spells - Ice Bolt", "AG", "NULL", "1/4", "directed spells", 0, 0, 0, 1, 0, 5, 13, 0, 27, 45], "286": ["Directed Spells - Nether Bolt", "AG", "NULL", "1/4", "directed spells", 0, 0, 0, 0, 0, 0, 13, 0, 27, 40], "263": ["Hygiene", "CO/SD", "NULL", "4", "body development", 0, 0, 0, 1, 0, 5, 5, 0, 0, 10], "262": ["Holding Breath", "CO/SD", "NULL", "8", "body development", 0, 0, 0, 0, 0, 0, 5, 0, 0, 5], "261": ["Focus", "SD", "NULL", "18", "arms", 0, 0, 0, 0, 0, 0, -2, 0, 0, -2], "260": ["Feinting", "QU/PR", "NULL", "6", "arms", 0, 0, 0, 0, 0, 0, 25, 0, 0, 25], "267": ["Prepared Shot", "SD/IN", "NULL", "6", "concentration", 0, 0, 0, 0, 0, 0, 3, 0, 9, 12], "266": ["Moving Strike", "AG/SD", "NULL", "20", "arms", 0, 0, 0, 0, 0, 0, 5, 0, 0, 5], "265": ["Mind Block", "SD/PR", "NULL", "11", "general", 0, 0, 0, 0, 0, 0, 14, 0, 0, 14], "264": ["Intimidation", "PR/RE", "NULL", "2/5", "social", 0, 0, 0, 0, 0, 0, 20, 0, 0, 20], "269": ["Taunting", "IN", "NULL", "7", "subterfuge", 0, 0, 0, 0, 0, 0, 9, 0, 0, 9], "268": ["Seaborne Combat", "AG/AG/IN", "NULL", "3", "athletic", 0, 0, 0, 0, 0, 0, 11, 0, 0, 11], "59": ["Drug Tolerance", "CO/SD", "NULL", "3/6", "medical", 0, 0, 0, 0, 0, 0, 5, 0, 0, 5], "58": ["Driving", "AG/QU", "NULL", "3", "outdoor", 0, 0, 0, 0, 0, 0, 16, 0, 0, 16], "emmb": 0, "55": ["Dowsing", "EM", "NULL", "1/3", "concentration", 0, 0, 0, 0, 0, 0, 17, 0, 9, 26], "54": ["Diving", "SD/AG", "NULL", "3", "athletic", 0, 0, 0, 0, 0, 0, 5, 0, 0, 5], "57": ["Dragon Lore", "ME/RE", "NULL", "1/3", "academic", 0, 0, 0, 3, 0, 15, 21, 0, 18, 54], "56": ["Drafting", "RE/ME", "NULL", "2/5", "academic", 0, 0, 0, 0, 0, 0, 21, 0, 18, 39], "51": ["Disguise", "PR/SD", "NULL", "3/6", "subterfuge", 0, 0, 0, 0, 0, 0, 14, 0, 0, 14], "50": ["Disarm Trap", "IN/AG", "NULL", "7", "subterfuge", 0, 0, 0, 0, 0, 0, 11, 0, 0, 11], "53": ["Divination", "IN/EM", "NULL", "2/4", "magical", 0, 0, 0, 0, 0, 0, 13, 0, 27, 40], "52": ["Distance Running", "CO", "NULL", "3", "athletic", 0, 0, 0, 0, 0, 0, 12, 0, 0, 12], "259": ["Donning/Doffing Armor:Plate", "QU/AG", "NULL", "11", "arms", 0, 0, 0, 0, 0, 0, 16, 0, 0, 16], "pr_pot": 76, "67": ["Flora Lore", "ME/RE", "NULL", "2/5", "academic", 0, 0, 0, 1, 0, 5, 21, 0, 18, 44], "115": ["Meditation: Sleep", "SD/IN", "NULL", "1/4", "concentration", 0, 0, 0, 0, 0, 0, 3, 0, 9, 12], "114": ["Meditation: Ki", "SD/PR", "NULL", "3/5", "concentration", 0, 0, 0, 0, 0, 0, 14, 0, 9, 23], "117": ["Metal Evaluation", "IN/RE", "NULL", "2/5", "general", 0, 0, 0, 0, 0, 0, 9, 0, 0, 9], "116": ["Meditation: Trance", "PR/SD", "NULL", "1/3", "concentration", 0, 0, 0, 1, 0, 5, 14, 0, 9, 28], "111": ["Meditation: Cleansing", "SD/EM", "NULL", "2/4", "concentration", 0, 0, 0, 0, 0, 0, 7, 0, 9, 16], "110": ["Mechanition", "RE/AG", "NULL", "2/6", "academic", 0, 0, 0, 0, 0, 0, 11, 0, 18, 29], "113": ["Meditation: Healing", "SD/EM", "NULL", "2/4", "concentration", 0, 0, 0, 0, 0, 0, 7, 0, 9, 16], "253": ["Dentistry", "ME/AG", "NULL", "6", "medical", 0, 0, 0, 0, 0, 0, 23, 0, 0, 23], "119": ["Midwifery", "EM/ME/IN", "NULL", "4", "medical", 0, 0, 0, 0, 0, 0, 19, 0, 0, 19], "118": ["Metal Lore", "ME/RE", "NULL", "1/4", "academic", 0, 0, 0, 0, 0, 0, 21, 0, 18, 39], "ag_stat": 86, "qu_stat": 90, "intb": 9, "me_stat": 86, "next_lvl": 150000, "ag_pot": 86, "inmb": 0, "229": ["Short Bow", "AG/AG/ST", "Missile", "20", "arms", 0, 0, 0, 0, 0, 0, 12, 0, 0, 12], "228": ["Scimitar", "ST/ST/AG", "1-HS", "20", "arms", 0, 0, 0, 0, 0, 0, 11, 0, 0, 11], "227": ["Rapier", "ST/ST/AG", "1-HS", "20", "arms", 0, 0, 0, 0, 0, 0, 11, 0, 0, 11], "226": ["Quarterstaff", "ST/ST/AG", "2-H", "9", "arms", 0, 1, 1, 6, 0, 40, 11, 0, 0, 51], "225": ["Polearm", "ST/ST/AG", "Polearm", "20", "arms", 0, 0, 0, 0, 0, 0, 11, 0, 0, 11], "224": ["Morning Star", "ST/ST/AG", "1-HC", "20", "arms", 0, 0, 0, 0, 0, 0, 11, 0, 0, 11], "223": ["Main Gauche", "ST/ST/AG", "1-HS", "20", "arms", 0, 0, 0, 0, 0, 0, 11, 0, 0, 11], "222": ["Mace", "ST/ST/AG", "1-HC", "20", "arms", 0, 0, 0, 0, 0, 0, 11, 0, 0, 11], "221": ["Long Bow", "AG/AG/ST", "Missile", "20", "arms", 0, 0, 0, 0, 0, 0, 12, 0, 0, 12], "220": ["Light Crossbow", "AG/AG/ST", "Missile", "20", "arms", 0, 0, 0, 0, 0, 0, 12, 0, 0, 12], "hair": "Blonde", "lvl": 9, "FullName": "Uldar Brightwood", "151": ["Sailing", "AG/IN", "NULL", "3", "athletic", 0, 0, 0, 0, 0, 0, 11, 0, 0, 11], "150": ["Runes", "EM/IN", "NULL", "1/4", "magical", 0, 0, 1, 6, 0, 35, 13, 0, 27, 75], "153": ["Sculpting", "IN/AG", "NULL", "2/4", "general", 0, 0, 0, 0, 0, 0, 11, 0, 0, 11], "152": ["Sanity Healing Lore", "ME/EM", "NULL", "2", "academic", 0, 0, 0, 0, 0, 0, 25, 0, 18, 43], "155": ["Second Aid", "SD/EM/IN", "NULL", "3/7", "medical", 0, 0, 0, 0, 0, 0, 8, 0, 0, 8], "154": ["Scrounge", "IN/RE", "NULL", "2/6", "outdoor", 0, 0, 0, 0, 0, 0, 9, 0, 0, 9], "157": ["Siege Engineer", "RE/IN", "NULL", "2/4", "academic", 0, 0, 0, 0, 0, 0, 9, 0, 18, 27], "156": ["Seduction", "EM/PR", "NULL", "2/5", "social", 0, 0, 0, 0, 0, 0, 23, 0, 0, 23], "159": ["Sense Reality Warp", "IN/EM", "NULL", "1/3", "perception", 0, 0, 0, 0, 0, 0, 13, 0, 0, 13], "158": ["Sense Ambush/Assassin", "IN/RE", "NULL", "3", "perception", 0, 0, 1, 5, 0, 30, 9, 0, 0, 39], "112": ["Meditation: Death", "SD/PR", "NULL", "1/5", "concentration", 0, 0, 0, 0, 0, 0, 14, 0, 9, 23], "48": ["Disarm Foe: Armed", "AG", "NULL", "6", "arms", 0, 0, 0, 0, 0, 0, 13, 0, 0, 13], "49": ["Disarm Foe: Unarmed", "AG", "NULL", "9", "arms", 0, 0, 0, 0, 0, 0, 13, 0, 0, 13], "46": ["Diplomacy", "PR/IN", "NULL", "2/4", "social", 0, 0, 0, 0, 0, 0, 19, 0, 0, 19], "47": ["Direction Sense", "IN/RE", "NULL", "2/4", "perception", 0, 0, 0, 0, 0, 0, 9, 0, 0, 9], "44": ["Detect Traps", "IN", "NULL", "3", "perception", 0, 0, 0, 2, 0, 10, 9, 0, 0, 19], "45": ["Diagnostics", "IN/RE", "NULL", "3/6", "medical", 0, 0, 0, 1, 0, 5, 9, 0, 0, 14], "42": ["Dance", "AG/IN", "NULL", "2/6", "athletic", 0, 0, 0, 0, 0, 0, 11, 0, 0, 11], "43": ["Demon/Devil Lore", "ME/RE", "NULL", "1/2", "academic", 1, 1, 1, 8, 0, 52, 21, 0, 18, 91], "40": ["Cookery", "RE/AG", "NULL", "2/6", "general", 0, 1, 1, 2, 0, 20, 11, 0, 0, 31], "41": ["Crafting", "AG/SD", "NULL", "2/5", "general", 0, 0, 0, 0, 0, 0, 5, 0, 0, 5], "5": ["Adrenal Move: Landing", "PR/SD", "NULL", "6", "concentration", 0, 0, 0, 0, 0, 0, 14, 0, 9, 23], "shieldMeDB": "30", "me_pot": 86, "co_stat": 82, "mentmod": 10, "age": 75}
